databricks/__init__.py
databricks/connect/__init__.py
databricks/connect/auth.py
databricks/connect/cache.py
databricks/connect/cli.py
databricks/connect/debug.py
databricks/connect/env.py
databricks/connect/headers.py
databricks/connect/py.typed
databricks/connect/session.py
databricks/connect/uds_channel_builder.py
databricks/connect/validation.py
databricks/connect/version.py
databricks/connect/auto_dependencies/__init__.py
databricks/connect/auto_dependencies/cache.py
databricks/connect/auto_dependencies/discovery.py
databricks/connect/auto_dependencies/hook.py
databricks/connect/auto_dependencies/tarjan_scc.py
databricks/connect/pkginfo/__init__.py
databricks/connect/pkginfo/distribution.py
databricks/connect/pkginfo/sdist.py
databricks/connect/pkginfo/utils.py
databricks/connect/pkginfo/wheel.py
databricks/connect/scripts/register_pyspark_installation.py
databricks/service_credentials/__init__.py
databricks/service_credentials/credential_retriever.py
databricks/service_credentials/py.typed
databricks/service_credentials/servicecredentials.py
databricks/service_credentials/proto/__init__.py
databricks/service_credentials/proto/temporary_credential_pb2.py
databricks/service_credentials/proto/temporary_credential_pb2_grpc.py
databricks_connect-17.3.1.data/scripts/find-spark-home
databricks_connect-17.3.1.data/scripts/find-spark-home.cmd
databricks_connect-17.3.1.data/scripts/find_spark_home.py
databricks_connect-17.3.1.data/scripts/load-spark-env.sh
databricks_connect-17.3.1.data/scripts/pyspark
databricks_connect-17.3.1.data/scripts/spark-submit
databricks_connect-17.3.1.data/scripts/spark-submit.cmd
databricks_connect-17.3.1.data/scripts/spark-submit2.cmd
delta/__init__.py
delta/_typing.py
delta/pip_utils.py
delta/tables.py
delta/connect/__init__.py
delta/connect/_typing.py
delta/connect/exceptions.py
delta/connect/plan.py
delta/connect/tables.py
delta/connect/proto/__init__.py
delta/connect/proto/base_pb2.py
delta/connect/proto/commands_pb2.py
databricks_connect-17.3.1.dist-info/METADATA
databricks_connect-17.3.1.dist-info/WHEEL
databricks_connect-17.3.1.dist-info/entry_points.txt
databricks_connect-17.3.1.dist-info/top_level.txt
databricks_connect-17.3.1.dist-info/RECORD
