Metadata-Version: 2.1
Name: databricks-connect
Version: 17.3.1
Summary: Databricks Connect Client
Home-page: UNKNOWN
Author: Databricks
Author-email: feedback@databricks.com
License: Databricks Proprietary License
Platform: UNKNOWN
Classifier: Development Status :: 5 - Production/Stable
Classifier: License :: Other/Proprietary License
Classifier: Programming Language :: Python :: 3.12
Classifier: Programming Language :: Python :: Implementation :: CPython
Classifier: Programming Language :: Python :: Implementation :: PyPy
Provides: pyspark
Obsoletes: pyspark
Requires-Python: ==3.12.*
Requires-Dist: databricks-sdk (>=0.46.0)
Requires-Dist: googleapis-common-protos (>=1.65.0)
Requires-Dist: grpcio-status (>=1.67.0)
Requires-Dist: grpcio (>=1.67.0)
Requires-Dist: numpy (>=1.15)
Requires-Dist: packaging (>=23.2)
Requires-Dist: pandas (>=1.0.5)
Requires-Dist: py4j (<0.10.9.10,>=0.10.9.7)
Requires-Dist: pyarrow (>=10.0.0)
Requires-Dist: setuptools (>=68.0.0)
Requires-Dist: six
Requires-Dist: zstandard (>=0.23.0)
Provides-Extra: connect
Requires-Dist: googleapis-common-protos (>=1.65.0) ; extra == 'connect'
Requires-Dist: grpcio-status (>=1.67.0) ; extra == 'connect'
Requires-Dist: grpcio (>=1.67.0) ; extra == 'connect'
Requires-Dist: numpy (>=1.21) ; extra == 'connect'
Requires-Dist: pandas (>=1.0.5) ; extra == 'connect'
Requires-Dist: pyarrow (>=10.0.0) ; extra == 'connect'
Requires-Dist: zstandard (>=0.23.0) ; extra == 'connect'
Provides-Extra: ml
Requires-Dist: numpy (>=1.21) ; extra == 'ml'
Provides-Extra: mllib
Requires-Dist: numpy (>=1.21) ; extra == 'mllib'
Provides-Extra: pandas_on_spark
Requires-Dist: numpy (>=1.21) ; extra == 'pandas_on_spark'
Requires-Dist: pandas (>=1.0.5) ; extra == 'pandas_on_spark'
Requires-Dist: pyarrow (>=10.0.0) ; extra == 'pandas_on_spark'
Provides-Extra: pipelines
Requires-Dist: googleapis-common-protos (>=1.65.0) ; extra == 'pipelines'
Requires-Dist: grpcio-status (>=1.67.0) ; extra == 'pipelines'
Requires-Dist: grpcio (>=1.67.0) ; extra == 'pipelines'
Requires-Dist: numpy (>=1.21) ; extra == 'pipelines'
Requires-Dist: pandas (>=1.0.5) ; extra == 'pipelines'
Requires-Dist: pyarrow (>=10.0.0) ; extra == 'pipelines'
Requires-Dist: pyyaml (>=3.11) ; extra == 'pipelines'
Requires-Dist: zstandard (>=0.23.0) ; extra == 'pipelines'
Provides-Extra: sql
Requires-Dist: numpy (>=1.21) ; extra == 'sql'
Requires-Dist: pandas (>=1.0.5) ; extra == 'sql'
Requires-Dist: pyarrow (>=10.0.0) ; extra == 'sql'
